torchmultimodal/__init__.py
torchmultimodal/diffusion_labs/__init__.py
torchmultimodal/diffusion_labs/models/__init__.py
torchmultimodal/diffusion_labs/models/adm_unet/__init__.py
torchmultimodal/diffusion_labs/models/adm_unet/adm.py
torchmultimodal/diffusion_labs/models/adm_unet/attention_block.py
torchmultimodal/diffusion_labs/models/adm_unet/res_block.py
torchmultimodal/diffusion_labs/models/dalle2/__init__.py
torchmultimodal/diffusion_labs/models/dalle2/dalle2_decoder.py
torchmultimodal/diffusion_labs/models/dalle2/transforms.py
torchmultimodal/diffusion_labs/models/vae/__init__.py
torchmultimodal/diffusion_labs/models/vae/attention.py
torchmultimodal/diffusion_labs/models/vae/encoder_decoder.py
torchmultimodal/diffusion_labs/models/vae/res_block.py
torchmultimodal/diffusion_labs/models/vae/residual_sampling.py
torchmultimodal/diffusion_labs/models/vae/vae.py
torchmultimodal/diffusion_labs/modules/__init__.py
torchmultimodal/diffusion_labs/modules/adapters/__init__.py
torchmultimodal/diffusion_labs/modules/adapters/adapter.py
torchmultimodal/diffusion_labs/modules/adapters/cfguidance.py
torchmultimodal/diffusion_labs/modules/adapters/inpainting.py
torchmultimodal/diffusion_labs/modules/adapters/super_resolution.py
torchmultimodal/diffusion_labs/modules/losses/__init__.py
torchmultimodal/diffusion_labs/modules/losses/diffusion_hybrid_loss.py
torchmultimodal/diffusion_labs/modules/losses/vlb_loss.py
torchmultimodal/diffusion_labs/predictors/__init__.py
torchmultimodal/diffusion_labs/predictors/noise_predictor.py
torchmultimodal/diffusion_labs/predictors/predictor.py
torchmultimodal/diffusion_labs/predictors/target_predictor.py
torchmultimodal/diffusion_labs/predictors/v_predictor.py
torchmultimodal/diffusion_labs/samplers/__init__.py
torchmultimodal/diffusion_labs/samplers/ddim.py
torchmultimodal/diffusion_labs/samplers/ddpm.py
torchmultimodal/diffusion_labs/samplers/sampler.py
torchmultimodal/diffusion_labs/schedules/__init__.py
torchmultimodal_nightly-2024.4.1.dist-info/LICENSE
torchmultimodal_nightly-2024.4.1.dist-info/METADATA
torchmultimodal_nightly-2024.4.1.dist-info/NOTICES
torchmultimodal_nightly-2024.4.1.dist-info/WHEEL
torchmultimodal_nightly-2024.4.1.dist-info/top_level.txt
torchmultimodal_nightly-2024.4.1.dist-info/RECORD
