Metadata-Version: 2.1
Name: torchmultimodal-nightly
Version: 2024.4.1
Summary: PyTorch Multimodal Library
Home-page: https://github.com/facebookresearch/multimodal
Author: PyTorch Multimodal Team
Author-email: torchmultimodal@fb.com
Classifier: Development Status :: 4 - Beta
Classifier: Intended Audience :: Developers
Classifier: Intended Audience :: Science/Research
Classifier: License :: OSI Approved :: BSD License
Classifier: Topic :: Scientific/Engineering :: Artificial Intelligence
Classifier: Programming Language :: Python :: 3.7
Classifier: Programming Language :: Python :: 3.8
Classifier: Programming Language :: Python :: 3.9
Requires-Python: >=3.7
License-File: LICENSE
License-File: NOTICES
Requires-Dist: DALL-E ==0.1
Requires-Dist: iopath
Requires-Dist: attrs ==23.1.0
Requires-Dist: ftfy
Requires-Dist: regex
Provides-Extra: dev
Requires-Dist: DALL-E ==0.1 ; extra == 'dev'
Requires-Dist: black ==22.12.0 ; extra == 'dev'
Requires-Dist: flake8-bugbear ==22.4.25 ; extra == 'dev'
Requires-Dist: flake8 ==4.0.1 ; extra == 'dev'
Requires-Dist: iopath ; extra == 'dev'
Requires-Dist: mypy ==1.8.0 ; extra == 'dev'
Requires-Dist: pep8-naming ==0.12.1 ; extra == 'dev'
Requires-Dist: pre-commit ; extra == 'dev'
Requires-Dist: pytest ; extra == 'dev'
Requires-Dist: pytest-cov ; extra == 'dev'
Requires-Dist: pytest-mock ==3.8.2 ; extra == 'dev'
Requires-Dist: ufmt ==2.0.1 ; extra == 'dev'
Requires-Dist: usort ==1.0.5 ; extra == 'dev'
